pydiffmap/__init__.py
pydiffmap/diffusion_map.py
pydiffmap/kernel.py
pydiffmap/utils.py
pydiffmap/visualization.py
pydiffmap-0.2.0.1.dist-info/METADATA
pydiffmap-0.2.0.1.dist-info/RECORD
pydiffmap-0.2.0.1.dist-info/WHEEL
pydiffmap-0.2.0.1.dist-info/top_level.txt
