Metadata-Version: 2.1
Name: pydiffmap
Version: 0.2.0.1
Summary: Library for constructing variable bandwidth diffusion maps
Home-page: https://github.com/DiffusionMapsAcademics/pyDiffMap
Author: Ralf Banisch, Erik Henning Thiede, Zofia Trstanova
Author-email: ralf.banisch@fu-berlin.de, ehthiede@gmail.com, zofia.trstanova@ed.ac.uk
License: MIT license
Keywords: diffusion maps,manifold learning,molecular dynamics,dimensionality reduction
Platform: UNKNOWN
Classifier: Development Status :: 3 - Alpha
Classifier: Topic :: Scientific/Engineering
Classifier: Intended Audience :: Science/Research
Classifier: License :: OSI Approved :: MIT License
Classifier: Operating System :: Unix
Classifier: Operating System :: POSIX
Classifier: Operating System :: Microsoft :: Windows
Classifier: Programming Language :: Python
Classifier: Programming Language :: Python :: 2.7
Classifier: Programming Language :: Python :: 3
Classifier: Programming Language :: Python :: 3.4
Classifier: Programming Language :: Python :: 3.5
Classifier: Programming Language :: Python :: 3.6
Classifier: Programming Language :: Python :: 3.7
Classifier: Topic :: Scientific/Engineering
Requires-Dist: numpy
Requires-Dist: scipy
Requires-Dist: scikit-learn
Requires-Dist: matplotlib
Requires-Dist: six
Requires-Dist: numexpr
